{
  "kind": "singleType",
  "collectionName": "homes",
  "info": {
    "singularName": "home",
    "pluralName": "homes",
    "displayName": "Home"
  },
  "options": {
    "draftAndPublish": true
  },
  "pluginOptions": {},
  "attributes": {
    "content": {
      "type": "dynamiczone",
      "components": [
        "hero.hero-2",
        "hero.search-integration",
        "hero.hero-1",
        "hero.hero-3",
        "grids.grid-1",
        "filters.filter-1",
        "relational.logo-grid",
        "relational.certifications",
        "relational.testimonials",
        "updates.update-marquee",
        "pre-footer.pre-footer"
      ]
    }
  }
}
